vasprun/IR.py
vasprun/__init__.py
vasprun/version.py
vasprun_xml-1.0.4.data/scripts/vasprun
vasprun_xml-1.0.4.dist-info/METADATA
vasprun_xml-1.0.4.dist-info/WHEEL
vasprun_xml-1.0.4.dist-info/top_level.txt
vasprun_xml-1.0.4.dist-info/RECORD
